{
  "name": "hypromellose",
  "functional_class": "thickener",
  "allergens": [],
  "vegan": true,
  "kosher": null,
  "halal": null,
  "e_number": "E464",
  "description": "Hypromellose is a cellulose-derived polymer used as a thickener in food products to improve texture and consistency.",
  "raw_text": "Hydroxypropyl Methylcellulose (Explained + Products) Products Ingredients Decode INCI Login Register Login Register Products Ingredients Decode INCI Follow us on our new Insta page » Hydroxypropyl Methylcellulose What-it-does: surfactant/cleansing , viscosity controlling , emulsion stabilising Irritancy: 0 Comedogenicity: 1 Official CosIng Information All Functions: antistatic, binding, emulsion stabilising, film forming, surfactant, viscosity controlling Description: cellulose, 2-hydroxypropyl methyl ether CAS #: 9004-65-3 Ph. Eur. Name: Methylhydroxypropylcellulosum Details A handy helper ingredient (a polymer, i.e. big molecule from repeated subunits) that is used to stabilize emulsions as well as to thicken up products . It can also stabilize foam in cleansing products. [more] [more] [less] Something incorrect or missing? Let us know! Products with Hydroxypropyl Methylcellulose Karuna Spot Melting Boost Lash Factor Pro Night-time Serum | Lashes & Brows spotlight oral care Whitening Strips Beautenic Salicylic Acid Serum Beautenic Sylcylic Acid 2% Serum Casandra Serum Vit C DMK Exoderma Peel-Gentle Exfoliant Erha21 Collagen Mask LaCabine Flash Effect Mazton skin solutions Lumexa Serum Metrosa Metronidazol Natural elements Clarifying Face Wash Target Tretin Ava Laboratorium Quintessence Of Beauty Skin Lifting Laser Ava Laboratorium Youth Cocktail Lifting Pearl BABOR 3d Firming BABOR Lift Express BALANCE active formula Dragon's Blood Instant Lifting Serum Boucléme Colour Toning Drops Cien Refreshing Facial Wash Cosmetic Plant Lift Up - Ser Lift Instant Cu Acid Hialuronic, Liftonin®-Xpress Și Extract De Magnolie Creightons Balance Active Formula Gold Collagen Rejuvenating Serum Eubos IN A SECOND Wow Now Lift Boost Freederm Gel Gladskin Acne Gel Gynofit Milchsäure Vaginal-Gel (Lactic Acid Vaginal Gel) Harmony Conditioning Temporary Hair Colour MEDI-PEEL Lif-tox Ampoule MEDI-PEEL Pore 9 Tightening Serum Neutrogena Stubborn Am Acne Treatment PMD Cleanse: Soothing Antioxidant Cleanser REN Instant Firming Beauty Shot Raww Watermelon Fresh Setting Spray Renee Rouleau Moisture Protecting Cleanser Supermood Egoboost Eyes Wide Open Serum Supermood Egoboost One Minute Facelift Serum Vagivital Moisturizing V Cleanser Amazon Basics 10% Benzoyl Peroxide Acne Medication, Maximum Strength As I Am Curl Clarity Shampoo CVS Health Maximum Strength Acne Treatment Gel (10% Benzoyl Peroxide Acne Medication) Clean & Clear Persa-Gel 10, Maximum Strength Conscious Chemist Salicylic Acid Serum Daylogic Acne Treatment Medicated Gel Dr. Barbara Stürm Lifting Serum Dr. Barbara Stürm Super Anti-Aging Serum EVENPRIME Cleanser Equate Beauty Acne Treatment Gel Freezeframe Instant V-Lift Serum Hello Lavender Vanilla Roll-on Deodorant L300 For Men Deo Roll-on Next page >> We do a Best of INCIDecoder email once a month with the most interesting products and ingredients we bump into. An error has occurred. Please try again later! Click below to subscribe: Thanks. :) You are almost done: please check your mailbox to confirm your email! *INCI is a list of the standardized and internationally accepted names used in the declaration of ingredients on cosmetic and personal care products. It is published by the Personal Care Product Council. Copyright 2026 | About",
  "sources": [
    "https://www.incidecoder.com/ingredients/hypromellose"
  ],
  "confidence": 0.3
}